fh2_drc_mcp_server/__init__.py
fh2_drc_mcp_server/__main__.py
fh2_drc_mcp_server/config/__init__.py
fh2_drc_mcp_server/config/settings.py
fh2_drc_mcp_server/core/__init__.py
fh2_drc_mcp_server/core/cache.py
fh2_drc_mcp_server/core/http_client.py
fh2_drc_mcp_server/core/mock_data.py
fh2_drc_mcp_server/models/__init__.py
fh2_drc_mcp_server/models/enums.py
fh2_drc_mcp_server/server.py
fh2_drc_mcp_server/services/__init__.py
fh2_drc_mcp_server/services/ai_alert_service.py
fh2_drc_mcp_server/services/camera_service.py
fh2_drc_mcp_server/services/device_service.py
fh2_drc_mcp_server/services/flight_service.py
fh2_drc_mcp_server/services/map_service.py
fh2_drc_mcp_server/services/panoramic_service.py
fh2_drc_mcp_server/services/poi_service.py
fh2_drc_mcp_server/services/recording_service.py
fh2_drc_mcp_server/services/smart_flight_service.py
fh2_drc_mcp_server/services/status_service.py
fh2_drc_mcp_server/tests/__init__.py
fh2_drc_mcp_server/utils/__init__.py
fh2_drc_mcp_server/utils/helpers.py
fh2_drc_mcp_server-0.1.9.dist-info/WHEEL
fh2_drc_mcp_server-0.1.9.dist-info/entry_points.txt
fh2_drc_mcp_server-0.1.9.dist-info/METADATA
fh2_drc_mcp_server-0.1.9.dist-info/RECORD
